pennylane_sf/__init__.py
pennylane_sf/_version.py
pennylane_sf/expectations.py
pennylane_sf/fock.py
pennylane_sf/gaussian.py
pennylane_sf/gbs.py
pennylane_sf/ops.py
pennylane_sf/remote.py
pennylane_sf/simulator.py
pennylane_sf/tf.py
PennyLane_SF-0.29.0.dist-info/LICENSE
PennyLane_SF-0.29.0.dist-info/METADATA
PennyLane_SF-0.29.0.dist-info/WHEEL
PennyLane_SF-0.29.0.dist-info/entry_points.txt
PennyLane_SF-0.29.0.dist-info/top_level.txt
PennyLane_SF-0.29.0.dist-info/RECORD
