Metadata-Version: 2.1
Name: PennyLane-SF
Version: 0.29.0
Summary: Open source library for continuous-variable quantum computation
Home-page: https://github.com/XanaduAI/pennylane-sf
Maintainer: Xanadu Inc.
Maintainer-email: nathan@xanadu.ai
License: Apache License 2.0
Platform: UNKNOWN
Classifier: Development Status :: 4 - Beta
Classifier: Environment :: Console
Classifier: Intended Audience :: Science/Research
Classifier: License :: OSI Approved :: Apache Software License
Classifier: Natural Language :: English
Classifier: Operating System :: POSIX
Classifier: Operating System :: MacOS :: MacOS X
Classifier: Operating System :: POSIX :: Linux
Classifier: Operating System :: Microsoft :: Windows
Classifier: Programming Language :: Python
Classifier: Programming Language :: Python :: 3
Classifier: Programming Language :: Python :: 3.8
Classifier: Programming Language :: Python :: 3.9
Classifier: Programming Language :: Python :: 3.10
Classifier: Programming Language :: Python :: 3 :: Only
Classifier: Topic :: Scientific/Engineering :: Physics
Provides: pennylane_sf
Requires-Dist: strawberryfields (>=0.22)
Requires-Dist: pennylane (>=0.19)
